<?xml version="1.0" encoding="UTF-8" standalone="yes"?>
<p:sldLayout xmlns:a="http://schemas.openxmlformats.org/drawingml/2006/main" xmlns:r="http://schemas.openxmlformats.org/officeDocument/2006/relationships" xmlns:p="http://schemas.openxmlformats.org/presentationml/2006/main" type="blank" preserve="1"><p:cSld name="BLANK_1_1_1_1_1_1"><p:bg><p:bgPr><a:solidFill><a:schemeClr val="dk2"/></a:solidFill><a:effectLst/></p:bgPr></p:bg><p:spTree><p:nvGrpSpPr><p:cNvPr id="1" name=""/><p:cNvGrpSpPr/><p:nvPr/></p:nvGrpSpPr><p:grpSpPr><a:xfrm><a:off x="0" y="0"/><a:ext cx="0" cy="0"/><a:chOff x="0" y="0"/><a:chExt cx="0" cy="0"/></a:xfrm></p:grpSpPr><p:cxnSp><p:nvCxnSpPr><p:cNvPr id="5" name="Google Shape;54;p13"/><p:cNvCxnSpPr/><p:nvPr/></p:nvCxnSpPr><p:spPr><a:xfrm><a:off x="246960" y="230040"/><a:ext cx="8664120" cy="360"/></a:xfrm><a:prstGeom prst="straightConnector1"><a:avLst/></a:prstGeom><a:ln w="19050"><a:solidFill><a:srgbClr val="1F1047"/></a:solidFill><a:round/></a:ln></p:spPr></p:cxnSp><p:sp><p:nvSpPr><p:cNvPr id="6" name="PlaceHolder 1"/><p:cNvSpPr><a:spLocks noGrp="1"/></p:cNvSpPr><p:nvPr><p:ph type="title"/></p:nvPr></p:nvSpPr><p:spPr><a:xfrm><a:off x="228600" y="228600"/><a:ext cx="8686800" cy="571320"/></a:xfrm><a:prstGeom prst="rect"><a:avLst/></a:prstGeom><a:noFill/><a:ln w="0"><a:noFill/></a:ln></p:spPr><p:txBody><a:bodyPr lIns="91440" tIns="91440" rIns="91440" bIns="91440" anchor="t"><a:noAutofit/></a:bodyPr><a:lstStyle/><a:p><a:pPr indent="0"><a:buNone/></a:pPr><a:r><a:rPr lang="fr-FR" sz="3000" b="0" u="none" strike="noStrike"><a:solidFill><a:schemeClr val="dk1"/></a:solidFill><a:effectLst/><a:uFillTx/><a:latin typeface="Arial"/></a:rPr><a:t>Click to edit the title text format</a:t></a:r></a:p></p:txBody></p:sp><p:sp><p:nvSpPr><p:cNvPr id="7" name="PlaceHolder 2"/><p:cNvSpPr><a:spLocks noGrp="1"/></p:cNvSpPr><p:nvPr><p:ph type="title"/></p:nvPr></p:nvSpPr><p:spPr><a:xfrm><a:off x="228600" y="1332000"/><a:ext cx="735840" cy="535320"/></a:xfrm><a:prstGeom prst="rect"><a:avLst/></a:prstGeom><a:noFill/><a:ln w="0"><a:noFill/></a:ln></p:spPr><p:txBody><a:bodyPr lIns="91440" tIns="91440" rIns="91440" bIns="91440" anchor="ctr"><a:noAutofit/></a:bodyPr><a:lstStyle/><a:p><a:pPr indent="0" algn="ctr"><a:lnSpc><a:spcPct val="100000"/></a:lnSpc><a:buNone/></a:pPr><a:r><a:rPr lang="fr-FR" sz="3500" b="0" u="none" strike="noStrike"><a:solidFill><a:schemeClr val="dk1"/></a:solidFill><a:effectLst/><a:uFillTx/><a:latin typeface="Cooper Black"/><a:ea typeface="Cooper Black"/></a:rPr><a:t>xx%</a:t></a:r><a:endParaRPr lang="fr-FR" sz="3500" b="0" u="none" strike="noStrike"><a:solidFill><a:schemeClr val="dk1"/></a:solidFill><a:effectLst/><a:uFillTx/><a:latin typeface="Arial"/></a:endParaRPr></a:p></p:txBody></p:sp><p:sp><p:nvSpPr><p:cNvPr id="8" name="PlaceHolder 3"/><p:cNvSpPr><a:spLocks noGrp="1"/></p:cNvSpPr><p:nvPr><p:ph type="title"/></p:nvPr></p:nvSpPr><p:spPr><a:xfrm><a:off x="228600" y="3192840"/><a:ext cx="735840" cy="535320"/></a:xfrm><a:prstGeom prst="rect"><a:avLst/></a:prstGeom><a:noFill/><a:ln w="0"><a:noFill/></a:ln></p:spPr><p:txBody><a:bodyPr lIns="91440" tIns="91440" rIns="91440" bIns="91440" anchor="ctr"><a:noAutofit/></a:bodyPr><a:lstStyle/><a:p><a:pPr indent="0" algn="ctr"><a:lnSpc><a:spcPct val="100000"/></a:lnSpc><a:buNone/></a:pPr><a:r><a:rPr lang="fr-FR" sz="3500" b="0" u="none" strike="noStrike"><a:solidFill><a:schemeClr val="dk1"/></a:solidFill><a:effectLst/><a:uFillTx/><a:latin typeface="Cooper Black"/><a:ea typeface="Cooper Black"/></a:rPr><a:t>xx%</a:t></a:r><a:endParaRPr lang="fr-FR" sz="3500" b="0" u="none" strike="noStrike"><a:solidFill><a:schemeClr val="dk1"/></a:solidFill><a:effectLst/><a:uFillTx/><a:latin typeface="Arial"/></a:endParaRPr></a:p></p:txBody></p:sp><p:sp><p:nvSpPr><p:cNvPr id="9" name="PlaceHolder 4"/><p:cNvSpPr><a:spLocks noGrp="1"/></p:cNvSpPr><p:nvPr><p:ph type="title"/></p:nvPr></p:nvSpPr><p:spPr><a:xfrm><a:off x="228600" y="2262960"/><a:ext cx="735840" cy="535320"/></a:xfrm><a:prstGeom prst="rect"><a:avLst/></a:prstGeom><a:noFill/><a:ln w="0"><a:noFill/></a:ln></p:spPr><p:txBody><a:bodyPr lIns="91440" tIns="91440" rIns="91440" bIns="91440" anchor="ctr"><a:noAutofit/></a:bodyPr><a:lstStyle/><a:p><a:pPr indent="0" algn="ctr"><a:lnSpc><a:spcPct val="100000"/></a:lnSpc><a:buNone/></a:pPr><a:r><a:rPr lang="fr-FR" sz="3500" b="0" u="none" strike="noStrike"><a:solidFill><a:schemeClr val="dk1"/></a:solidFill><a:effectLst/><a:uFillTx/><a:latin typeface="Cooper Black"/><a:ea typeface="Cooper Black"/></a:rPr><a:t>xx%</a:t></a:r><a:endParaRPr lang="fr-FR" sz="3500" b="0" u="none" strike="noStrike"><a:solidFill><a:schemeClr val="dk1"/></a:solidFill><a:effectLst/><a:uFillTx/><a:latin typeface="Arial"/></a:endParaRPr></a:p></p:txBody></p:sp><p:sp><p:nvSpPr><p:cNvPr id="10" name="PlaceHolder 5"/><p:cNvSpPr><a:spLocks noGrp="1"/></p:cNvSpPr><p:nvPr><p:ph type="title"/></p:nvPr></p:nvSpPr><p:spPr><a:xfrm><a:off x="228600" y="4122720"/><a:ext cx="735840" cy="535320"/></a:xfrm><a:prstGeom prst="rect"><a:avLst/></a:prstGeom><a:noFill/><a:ln w="0"><a:noFill/></a:ln></p:spPr><p:txBody><a:bodyPr lIns="91440" tIns="91440" rIns="91440" bIns="91440" anchor="ctr"><a:noAutofit/></a:bodyPr><a:lstStyle/><a:p><a:pPr indent="0" algn="ctr"><a:lnSpc><a:spcPct val="100000"/></a:lnSpc><a:buNone/></a:pPr><a:r><a:rPr lang="fr-FR" sz="3500" b="0" u="none" strike="noStrike"><a:solidFill><a:schemeClr val="dk1"/></a:solidFill><a:effectLst/><a:uFillTx/><a:latin typeface="Cooper Black"/><a:ea typeface="Cooper Black"/></a:rPr><a:t>xx%</a:t></a:r><a:endParaRPr lang="fr-FR" sz="3500" b="0" u="none" strike="noStrike"><a:solidFill><a:schemeClr val="dk1"/></a:solidFill><a:effectLst/><a:uFillTx/><a:latin typeface="Arial"/></a:endParaRPr></a:p></p:txBody></p:sp><p:sp><p:nvSpPr><p:cNvPr id="11" name="PlaceHolder 6"/><p:cNvSpPr><a:spLocks noGrp="1"/></p:cNvSpPr><p:nvPr><p:ph type="title"/></p:nvPr></p:nvSpPr><p:spPr><a:xfrm><a:off x="4675680" y="1332000"/><a:ext cx="735840" cy="535320"/></a:xfrm><a:prstGeom prst="rect"><a:avLst/></a:prstGeom><a:noFill/><a:ln w="0"><a:noFill/></a:ln></p:spPr><p:txBody><a:bodyPr lIns="91440" tIns="91440" rIns="91440" bIns="91440" anchor="ctr"><a:noAutofit/></a:bodyPr><a:lstStyle/><a:p><a:pPr indent="0" algn="ctr"><a:lnSpc><a:spcPct val="100000"/></a:lnSpc><a:buNone/></a:pPr><a:r><a:rPr lang="fr-FR" sz="3500" b="0" u="none" strike="noStrike"><a:solidFill><a:schemeClr val="dk1"/></a:solidFill><a:effectLst/><a:uFillTx/><a:latin typeface="Cooper Black"/><a:ea typeface="Cooper Black"/></a:rPr><a:t>xx%</a:t></a:r><a:endParaRPr lang="fr-FR" sz="3500" b="0" u="none" strike="noStrike"><a:solidFill><a:schemeClr val="dk1"/></a:solidFill><a:effectLst/><a:uFillTx/><a:latin typeface="Arial"/></a:endParaRPr></a:p></p:txBody></p:sp><p:sp><p:nvSpPr><p:cNvPr id="12" name="PlaceHolder 7"/><p:cNvSpPr><a:spLocks noGrp="1"/></p:cNvSpPr><p:nvPr><p:ph type="title"/></p:nvPr></p:nvSpPr><p:spPr><a:xfrm><a:off x="4675680" y="3192840"/><a:ext cx="735840" cy="535320"/></a:xfrm><a:prstGeom prst="rect"><a:avLst/></a:prstGeom><a:noFill/><a:ln w="0"><a:noFill/></a:ln></p:spPr><p:txBody><a:bodyPr lIns="91440" tIns="91440" rIns="91440" bIns="91440" anchor="ctr"><a:noAutofit/></a:bodyPr><a:lstStyle/><a:p><a:pPr indent="0" algn="ctr"><a:lnSpc><a:spcPct val="100000"/></a:lnSpc><a:buNone/></a:pPr><a:r><a:rPr lang="fr-FR" sz="3500" b="0" u="none" strike="noStrike"><a:solidFill><a:schemeClr val="dk1"/></a:solidFill><a:effectLst/><a:uFillTx/><a:latin typeface="Cooper Black"/><a:ea typeface="Cooper Black"/></a:rPr><a:t>xx%</a:t></a:r><a:endParaRPr lang="fr-FR" sz="3500" b="0" u="none" strike="noStrike"><a:solidFill><a:schemeClr val="dk1"/></a:solidFill><a:effectLst/><a:uFillTx/><a:latin typeface="Arial"/></a:endParaRPr></a:p></p:txBody></p:sp><p:sp><p:nvSpPr><p:cNvPr id="13" name="PlaceHolder 8"/><p:cNvSpPr><a:spLocks noGrp="1"/></p:cNvSpPr><p:nvPr><p:ph type="title"/></p:nvPr></p:nvSpPr><p:spPr><a:xfrm><a:off x="4675680" y="2262960"/><a:ext cx="735840" cy="535320"/></a:xfrm><a:prstGeom prst="rect"><a:avLst/></a:prstGeom><a:noFill/><a:ln w="0"><a:noFill/></a:ln></p:spPr><p:txBody><a:bodyPr lIns="91440" tIns="91440" rIns="91440" bIns="91440" anchor="ctr"><a:noAutofit/></a:bodyPr><a:lstStyle/><a:p><a:pPr indent="0" algn="ctr"><a:lnSpc><a:spcPct val="100000"/></a:lnSpc><a:buNone/></a:pPr><a:r><a:rPr lang="fr-FR" sz="3500" b="0" u="none" strike="noStrike"><a:solidFill><a:schemeClr val="dk1"/></a:solidFill><a:effectLst/><a:uFillTx/><a:latin typeface="Cooper Black"/><a:ea typeface="Cooper Black"/></a:rPr><a:t>xx%</a:t></a:r><a:endParaRPr lang="fr-FR" sz="3500" b="0" u="none" strike="noStrike"><a:solidFill><a:schemeClr val="dk1"/></a:solidFill><a:effectLst/><a:uFillTx/><a:latin typeface="Arial"/></a:endParaRPr></a:p></p:txBody></p:sp><p:sp><p:nvSpPr><p:cNvPr id="14" name="PlaceHolder 9"/><p:cNvSpPr><a:spLocks noGrp="1"/></p:cNvSpPr><p:nvPr><p:ph type="title"/></p:nvPr></p:nvSpPr><p:spPr><a:xfrm><a:off x="4675680" y="4122720"/><a:ext cx="735840" cy="535320"/></a:xfrm><a:prstGeom prst="rect"><a:avLst/></a:prstGeom><a:noFill/><a:ln w="0"><a:noFill/></a:ln></p:spPr><p:txBody><a:bodyPr lIns="91440" tIns="91440" rIns="91440" bIns="91440" anchor="ctr"><a:noAutofit/></a:bodyPr><a:lstStyle/><a:p><a:pPr indent="0" algn="ctr"><a:lnSpc><a:spcPct val="100000"/></a:lnSpc><a:buNone/></a:pPr><a:r><a:rPr lang="fr-FR" sz="3500" b="0" u="none" strike="noStrike"><a:solidFill><a:schemeClr val="dk1"/></a:solidFill><a:effectLst/><a:uFillTx/><a:latin typeface="Cooper Black"/><a:ea typeface="Cooper Black"/></a:rPr><a:t>xx%</a:t></a:r><a:endParaRPr lang="fr-FR" sz="3500" b="0" u="none" strike="noStrike"><a:solidFill><a:schemeClr val="dk1"/></a:solidFill><a:effectLst/><a:uFillTx/><a:latin typeface="Arial"/></a:endParaRPr></a:p></p:txBody></p:sp></p:spTree></p:cSld><p:clrMapOvr><a:masterClrMapping/></p:clrMapOvr></p:sldLayout>